bluepm/__init__.py
bluepm/client.py
bluepm/schema.py
bluepm-0.7.0.dist-info/licenses/LICENSE
bluepm-0.7.0.dist-info/METADATA
bluepm-0.7.0.dist-info/WHEEL
bluepm-0.7.0.dist-info/top_level.txt
bluepm-0.7.0.dist-info/RECORD
