Metadata-Version: 2.4
Name: bluepm
Version: 0.7.0
Summary: A Python client for interacting with the Blue project management GraphQL API
Home-page: https://gitlab.com/bloohq/blue-python-module
Author: Emanuele Faja
Author-email: manny@blue.cc
Classifier: Programming Language :: Python :: 3
Classifier: License :: OSI Approved :: MIT License
Classifier: Operating System :: OS Independent
Requires-Python: >=3.6
License-File: LICENSE
Requires-Dist: certifi
Requires-Dist: charset-normalizer
Requires-Dist: idna
Requires-Dist: requests
Requires-Dist: urllib3
Requires-Dist: sgqlc
Dynamic: author
Dynamic: author-email
Dynamic: classifier
Dynamic: description
Dynamic: description-content-type
Dynamic: home-page
Dynamic: license-file
Dynamic: requires-dist
Dynamic: requires-python
Dynamic: summary
